calsipro/__init__.py
calsipro/background.py
calsipro/cli.py
calsipro/io.py
calsipro/library.py
calsipro/mask/__init__.py
calsipro/mask/intensity.py
calsipro/mask/reach.py
calsipro/mask/variance.py
calsipro/peak_calling/old.py
calsipro/peak_calling/statistics.py
calsipro/separate.py
calsipro/speed.py
calsipro/util.py
calsipro-1.0.1.dist-info/WHEEL
calsipro-1.0.1.dist-info/entry_points.txt
calsipro-1.0.1.dist-info/METADATA
calsipro-1.0.1.dist-info/RECORD
