Metadata-Version: 2.3
Name: calsipro
Version: 1.0.1
Summary: Calcium Signal Propagation Speed Analysis Library
Author: Simon Haendeler
Author-email: Simon Haendeler <opensource@haend.de>
Requires-Dist: bioio>=3.0.0
Requires-Dist: bioio-czi>=2.4.0
Requires-Dist: bioio-imageio>=1.3.0
Requires-Dist: bokeh>=3.1.1
Requires-Dist: click>=8.1.8
Requires-Dist: datashader>=0.15.2
Requires-Dist: ffmpeg-python>=0.2.0
Requires-Dist: matplotlib>=3.10.6
Requires-Dist: numba>=0.58.1
Requires-Dist: numpy>=1.24.4
Requires-Dist: openpyxl>=3.1.5
Requires-Dist: pillow>=10.4.0
Requires-Dist: polars>=1.8.2
Requires-Dist: pywavelets>=1.4.1
Requires-Dist: scikit-image>=0.25.2
Requires-Dist: scikit-learn>=1.7.2
Requires-Dist: scipy>=1.10.1
Requires-Python: >=3.10, <3.12
